MANIFEST.in
README.rst
setup.cfg
setup.py
c2c/__init__.py
c2c.sqlalchemy.rest.egg-info/PKG-INFO
c2c.sqlalchemy.rest.egg-info/SOURCES.txt
c2c.sqlalchemy.rest.egg-info/dependency_links.txt
c2c.sqlalchemy.rest.egg-info/not-zip-safe
c2c.sqlalchemy.rest.egg-info/requires.txt
c2c.sqlalchemy.rest.egg-info/top_level.txt
c2c/sqlalchemy/__init__.py
c2c/sqlalchemy/rest/__init__.py