Metadata-Version: 1.1
Name: c2c.sqlalchemy.rest
Version: 0.2.2
Summary: Add a REST interface to simple SQLAlchemy object
Home-page: http://github.com/sbrunner/c2c.sqlalchemy.rest
Author: Stéphane Brunner
Author-email: stephane.brunner@camptocamp.com
License: BSD
Keywords: sqlalchemy rest
Platform: UNKNOWN
Classifier: Development Status :: 4 - Beta
Classifier: Environment :: Console
Classifier: Intended Audience :: Developers
Classifier: License :: OSI Approved :: BSD License
Classifier: Programming Language :: Python
Classifier: Framework :: Buildout :: Recipe
Classifier: Topic :: System :: Installation/Setup
